astrokit/__init__.py
astrokit/_top_level_map.py
astrokit/ML/__init__.py
astrokit/ML/d2l.py
astrokit/ML/utils.py
astrokit/datasets/HSCDownloader.py
astrokit/datasets/__init__.py
astrokit/datasets/query.py
astrokit/datasets/data/eazy_filters/FILTER.RES.latest
astrokit/datasets/data/eazy_filters/FILTER.RES.latest.info
astrokit/datasets/data/observation/ESO_standard_stars.txt
astrokit/datasets/data/observation/baoextinct.dat
astrokit/datasets/data/observation/xinglong_safe_boundary.csv
astrokit/externals/sfdmap.py
astrokit/externals/HSC_pdr3/downloadCutout.py
astrokit/externals/HSC_pdr3/downloadPsf.py
astrokit/extinction/__init__.py
astrokit/extinction/extinction.py
astrokit/observation/__init__.py
astrokit/observation/iraf_partner.py
astrokit/observation/obstools.py
astrokit/phot/__init__.py
astrokit/phot/filters.py
astrokit/phot/photometry.py
astrokit/phot/utils.py
astrokit/photoz/__init__.py
astrokit/photoz/colorz.py
astrokit/photoz/template_fitting.py
astrokit/photoz/utils.py
astrokit/spec/__init__.py
astrokit/spec/utils.py
astrokit/toolbox/__init__.py
astrokit/toolbox/calculate.py
astrokit/toolbox/match.py
astrokit/toolbox/plot.py
astrokit/toolbox/utils.py
astrokit/wrapper/__init__.py
astrokit/wrapper/eazy.py
astrokit/wrapper/galfit.py
astrokit/wrapper/sextractor.py
astrokit/wrapper/stilts.py
astrokit-2025.5.2.dist-info/METADATA
astrokit-2025.5.2.dist-info/WHEEL
astrokit-2025.5.2.dist-info/licenses/LICENSE
astrokit-2025.5.2.dist-info/RECORD
