Metadata-Version: 2.4
Name: astrokit
Version: 2025.5.2
Summary: AstroKit: A Python ToolKit for Astronomy
Project-URL: Homepage, https://github.com/astro-zhurui/astrokit
Project-URL: Bug Tracker, https://github.com/astro-zhurui/astrokit/issues
Author-email: Rui Zhu <zhurui675@gmail.com>
License: MIT License
License-File: LICENSE
Classifier: Intended Audience :: Developers
Classifier: Intended Audience :: Science/Research
Classifier: License :: OSI Approved :: MIT License
Classifier: Operating System :: MacOS
Classifier: Operating System :: POSIX
Classifier: Operating System :: Unix
Classifier: Programming Language :: Python :: 3
Classifier: Programming Language :: Python :: 3.12
Classifier: Programming Language :: Python :: 3.13
Classifier: Topic :: Scientific/Engineering
Classifier: Topic :: Software Development
Requires-Python: >=3.12
